odoo/addons/queue_job_cron_jobrunner/README.rst
odoo/addons/queue_job_cron_jobrunner/__init__.py
odoo/addons/queue_job_cron_jobrunner/__manifest__.py
odoo/addons/queue_job_cron_jobrunner/data/ir_cron.xml
odoo/addons/queue_job_cron_jobrunner/i18n/it.po
odoo/addons/queue_job_cron_jobrunner/i18n/queue_job_cron_jobrunner.pot
odoo/addons/queue_job_cron_jobrunner/i18n/ro.po
odoo/addons/queue_job_cron_jobrunner/i18n/zh_CN.po
odoo/addons/queue_job_cron_jobrunner/models/__init__.py
odoo/addons/queue_job_cron_jobrunner/models/ir_cron.py
odoo/addons/queue_job_cron_jobrunner/models/queue_job.py
odoo/addons/queue_job_cron_jobrunner/readme/CONFIGURE.md
odoo/addons/queue_job_cron_jobrunner/readme/CONTRIBUTORS.md
odoo/addons/queue_job_cron_jobrunner/readme/DESCRIPTION.md
odoo/addons/queue_job_cron_jobrunner/readme/ROADMAP.md
odoo/addons/queue_job_cron_jobrunner/static/description/icon.png
odoo/addons/queue_job_cron_jobrunner/static/description/index.html
odoo/addons/queue_job_cron_jobrunner/tests/__init__.py
odoo/addons/queue_job_cron_jobrunner/tests/test_queue_job.py
odoo/addons/queue_job_cron_jobrunner/views/ir_cron.xml
odoo_addon_queue_job_cron_jobrunner-18.0.1.0.1.dist-info/METADATA
odoo_addon_queue_job_cron_jobrunner-18.0.1.0.1.dist-info/WHEEL
odoo_addon_queue_job_cron_jobrunner-18.0.1.0.1.dist-info/top_level.txt
odoo_addon_queue_job_cron_jobrunner-18.0.1.0.1.dist-info/RECORD
