Metadata-Version: 2.1
Name: odoo-addon-queue_job_cron_jobrunner
Version: 18.0.1.0.1
Requires-Python: >=3.10
Requires-Dist: odoo-addon-queue_job==18.0.*
Requires-Dist: odoo==18.0.*
Summary: Run jobs without a dedicated JobRunner
Home-page: https://github.com/OCA/queue
License: AGPL-3
Author: Camptocamp SA, Odoo Community Association (OCA)
Author-email: support@odoo-community.org
Classifier: Programming Language :: Python
Classifier: Framework :: Odoo
Classifier: Framework :: Odoo :: 18.0
Classifier: License :: OSI Approved :: GNU Affero General Public License v3
Classifier: Development Status :: 3 - Alpha
